CHANGELOG
COPYRIGHT
LICENSE.txt
MANIFEST.in
README.md
setup.cfg
setup.py
doc/Makefile
doc/conf.py
doc/index.rst
odoodoc.egg-info/PKG-INFO
odoodoc.egg-info/SOURCES.txt
odoodoc.egg-info/dependency_links.txt
odoodoc.egg-info/namespace_packages.txt
odoodoc.egg-info/not-zip-safe
odoodoc.egg-info/requires.txt
odoodoc.egg-info/top_level.txt
sphinxcontrib/__init__.py
sphinxcontrib/odoodoc/__init__.py