Metadata-Version: 1.1
Name: odoodoc
Version: 0.17
Summary: Odoo markup for Sphinx
Home-page: https://github.org/minorisa/odoodoc
Author: Minorisa, S.L.
Author-email: projectes.odoo@minorisa.net
License: BSD
Download-URL: http://pypi.python.org/pypi/odoodoc
Platform: any
Classifier: Development Status :: 3 - Alpha
Classifier: Environment :: Console
Classifier: Environment :: Web Environment
Classifier: Intended Audience :: Developers
Classifier: License :: OSI Approved :: BSD License
Classifier: Operating System :: OS Independent
Classifier: Programming Language :: Python
Classifier: Topic :: Documentation
Classifier: Topic :: Utilities
